distributions_acc
