Metadata-Version: 1.0
Name: distributions-acc
Version: 0.2
Summary: Gaussian and Binomial distributions
Home-page: UNKNOWN
Author: Andrea Cruz Castillo
Author-email: UNKNOWN
License: UNKNOWN
Platform: UNKNOWN
